windsor_ai/__init__.py
windsor_ai/cli.py
windsor_ai/client.py
windsor_ai/enums.py
windsor_ai/exceptions.py
windsor_ai/models.py
windsor_ai-0.2.0.dist-info/METADATA
windsor_ai-0.2.0.dist-info/WHEEL
windsor_ai-0.2.0.dist-info/entry_points.txt
windsor_ai-0.2.0.dist-info/top_level.txt
windsor_ai-0.2.0.dist-info/RECORD
